agralogics/__init__.py
agralogics/models/__init__.py
agralogics/models/base.py
agralogics/models/baseSoilGrids.py
agralogics/models/disease/__init__.py
agralogics/models/disease/powderymildew.py
agralogics/models/soil/__init__.py
agralogics/models/soil/soilHydraulicConductivity.py
agralogics/models/weather/__init__.py
agralogics/models/weather/chillhours.py
agralogics/models/weather/chillhours_3245.py
agralogics/models/weather/chillportions.py
agralogics/models/weather/growingdegreedays.py
agralogics/models/weather/leafwetnessduration.py
agralogics-1.0.10.dist-info/LICENSE
agralogics-1.0.10.dist-info/METADATA
agralogics-1.0.10.dist-info/WHEEL
agralogics-1.0.10.dist-info/top_level.txt
agralogics-1.0.10.dist-info/RECORD
